ALU.v
module ALU (
    input [3:0] A,
    input [3:0] B,
    input [2:0] ALU_Sel, // need to support 7 operations so 3-bit
    output reg [3:0] Result,
    output reg CarryOut 
    ); 
        always @(*) begin
        case (ALU_Sel)
            3'b000: {CarryOut, Result} = A + B;        // Addition
            3'b001: {CarryOut, Result} = A - B;        // Subtraction
            3'b010: Result = A & B;                    // AND
            3'b011: Result = A | B;                    // OR
            3'b100: Result = A ^ B;                    // XOR
            3'b101: Result = A << 1;                   // Left Shift
            3'b110: Result = A >> 1;                   // Right Shift
            3'b111: Result= ~A;                        // Not
            default: Result = 4'b0000;                 // Default: Zero output
        endcase
        // For non-addition/subtraction, CarryOut is set to 0
        if (ALU_Sel > 3'b001) CarryOut = 0;
    end
endmodule

ALUtb.v
module ALUtb;
    reg [3:0] A, B;
    reg [2:0] ALU_Sel;
    wire [3:0] Result;
    wire CarryOut;

    ALU uut (
        .A(A),
        .B(B),
        .ALU_Sel(ALU_Sel),
        .Result(Result),
        .CarryOut(CarryOut)
    );

    initial begin
    $dumpfile("waveform.vcd");  
    $dumpvars(0, ALUtb);
    end


    initial begin
        //Test addition
        A = 4'b0101; B = 4'b0011; ALU_Sel = 3'b000; #15;
        $display("Addition: %b + %b = %b, CarryOut: %b", A, B, Result, CarryOut);

        // Test subtraction
        A = 4'b0110; B = 4'b0010; ALU_Sel = 3'b001; #15;
        $display("Subtraction: %b - %b = %b, CarryOut: %b", A, B, Result, CarryOut);

        // Test and
        A = 4'b1100; B = 4'b1010; ALU_Sel = 3'b010; #15;
        $display("AND: %b & %b = %b", A, B, Result);

        // Test or
        A = 4'b1100; B = 4'b1010; ALU_Sel = 3'b011; #15;
        $display("OR: %b | %b = %b", A, B, Result);

        // Test xor
        A = 4'b1100; B = 4'b1010; ALU_Sel = 3'b100; #15;
        $display("XOR: %b ^ %b = %b", A, B, Result);

        // Test left shift
        A = 4'b0111; ALU_Sel = 3'b101; #15;
        $display("Left Shift: %b << 1 = %b", A, Result);

        // Test right shift
        A = 4'b0111; ALU_Sel = 3'b110; #15;
        $display("Right Shift: %b >> 1 = %b", A, Result);

        // Test NOT operation
        A = 4'b1010; ALU_Sel = 3'b111; #10;
        $display("NOT: ~%b = %b", A, Result);

        // Default
        A = 4'b0000; B = 4'b0000; ALU_Sel = 3'b111; #15;
        $display("Default: ALU_Sel = %b, Result = %b", ALU_Sel, Result);
        $finish;
    end
endmodule

waveform.vcd
$date
	Tue Dec 24 19:46:17 2024
$end
$version
	Icarus Verilog
$end
$timescale
	1s
$end
$scope module ALUtb $end
$var wire 4 ! Result [3:0] $end
$var wire 1 " CarryOut $end
$var reg 4 # A [3:0] $end
$var reg 3 $ ALU_Sel [2:0] $end
$var reg 4 % B [3:0] $end
$scope module uut $end
$var wire 4 & A [3:0] $end
$var wire 3 ' ALU_Sel [2:0] $end
$var wire 4 ( B [3:0] $end
$var reg 1 " CarryOut $end
$var reg 4 ) Result [3:0] $end
$upscope $end
$upscope $end
$enddefinitions $end
$comment Show the parameter values. $end
$dumpall
$end
#0
$dumpvars
b1000 )
b11 (
b0 '
b101 &
b11 %
b0 $
b101 #
0"
b1000 !
$end
#15
b100 !
b100 )
b1 $
b1 '
b10 %
b10 (
b110 #
b110 &
#30
b1000 !
b1000 )
b10 $
b10 '
b1010 %
b1010 (
b1100 #
b1100 &
#45
b1110 !
b1110 )
b11 $
b11 '
#60
b110 !
b110 )
b100 $
b100 '
#75
b1110 !
b1110 )
b101 $
b101 '
b111 #
b111 &
#90
b11 !
b11 )
b110 $
b110 '
#105
b101 !
b101 )
b111 $
b111 '
b1010 #
b1010 &
#115
b1111 !
b1111 )
b0 %
b0 (
b0 #
b0 &
